pypomes/__init__.py
pypomes/azure_pomes.py
pypomes/crypto_pomes.py
pypomes/datetime_pomes.py
pypomes/db_pomes.py
pypomes/dict_pomes.py
pypomes/email_pomes.py
pypomes/encoding_pomes.py
pypomes/env_pomes.py
pypomes/exception_pomes.py
pypomes/file_pomes.py
pypomes/json_pomes.py
pypomes/ldap_pomes.py
pypomes/list_pomes.py
pypomes/logging_pomes.py
pypomes/minio_pomes.py
pypomes/soap_pomes.py
pypomes/str_pomes.py
pypomes/xml_pomes.py
pypomes-0.2.0.dist-info/METADATA
pypomes-0.2.0.dist-info/WHEEL
pypomes-0.2.0.dist-info/licenses/LICENSE
pypomes-0.2.0.dist-info/RECORD
