Metadata-Version: 2.1
Name: pypomes
Version: 0.2.0
Summary: A collection of Python pomes, pennyeach
Project-URL: Homepage, https://github.com/TheWiseCoder/PyPomes
Project-URL: Bug Tracker, https://github.com/TheWiseCoder/PyPomes/issues
Author-email: GT Nunes <wisecoder01@gmail.com>
License-File: LICENSE
Classifier: License :: OSI Approved :: MIT License
Classifier: Operating System :: OS Independent
Classifier: Programming Language :: Python :: 3
Requires-Python: >=3.10
Requires-Dist: asn1crypto>=1.5.1
Requires-Dist: azure-common>=1.1.28
Requires-Dist: azure-core>=1.26.4
Requires-Dist: azure-identity>=1.13.0
Requires-Dist: azure-storage-blob>=12.16.0
Requires-Dist: cryptography>=41.0.1
Requires-Dist: flask>=2.3.2
Requires-Dist: lxml>=4.9.2
Requires-Dist: minio>=7.1.15
Requires-Dist: psycopg2-binary>=2.9.6
Requires-Dist: pyodbc>=4.0.39
Requires-Dist: python-dateutil>=2.8.2
Requires-Dist: python-ldap>=3.4.0
Requires-Dist: requests>=2.31.0
Requires-Dist: setuptools>=67.8.0
Requires-Dist: unidecode>=1.3.6
Requires-Dist: werkzeug>=2.3.6
Requires-Dist: wheel>=0.40.0
Requires-Dist: xmltodict3>=0.0.4
Requires-Dist: zeep>=4.2.1
